{
  "updated": "2026-03-06T06:50:42.923982+00:00",
  "status": "LIVE",
  "bars_processed": 200,
  "trades_today": 0,
  "win_rate": 0.0,
  "profit_factor": 0.0,
  "session_pnl_pct": 0.0,
  "signals_rejected": 50,
  "signals_approved": 0,
  "htf_bias": "NEUTRAL",
  "safety_rails": "OK",
  "modifiers": {
    "overnight": {
      "value": 1.0,
      "display": "1.0x (No data)"
    },
    "fomc": {
      "value": 1.0,
      "display": "1.0x (No data)"
    },
    "gamma": {
      "value": 1.0,
      "display": "1.0x (No data)"
    },
    "har_rv": {
      "value": 1.0,
      "display": "1.0x (No data)"
    }
  },
  "last_price": 25105.75,
  "recent_decisions": [
    {
      "time": "01:48:30 ET",
      "direction": "LONG",
      "decision": "REJECTED",
      "reason": "CONFLUENCE"
    },
    {
      "time": "01:48:36 ET",
      "direction": "LONG",
      "decision": "REJECTED",
      "reason": "CONFLUENCE"
    },
    {
      "time": "01:48:41 ET",
      "direction": "LONG",
      "decision": "REJECTED",
      "reason": "CONFLUENCE"
    },
    {
      "time": "01:49:00 ET",
      "direction": "SHORT",
      "decision": "REJECTED",
      "reason": "HTF_GATE"
    },
    {
      "time": "01:49:50 ET",
      "direction": "SHORT",
      "decision": "REJECTED",
      "reason": "HTF_GATE"
    },
    {
      "time": "01:50:21 ET",
      "direction": "SHORT",
      "decision": "REJECTED",
      "reason": "HTF_GATE"
    },
    {
      "time": "01:50:26 ET",
      "direction": "SHORT",
      "decision": "REJECTED",
      "reason": "HTF_GATE"
    },
    {
      "time": "01:50:31 ET",
      "direction": "SHORT",
      "decision": "REJECTED",
      "reason": "HTF_GATE"
    },
    {
      "time": "01:50:35 ET",
      "direction": "SHORT",
      "decision": "REJECTED",
      "reason": "HTF_GATE"
    },
    {
      "time": "01:50:41 ET",
      "direction": "SHORT",
      "decision": "REJECTED",
      "reason": "HTF_GATE"
    }
  ]
}