{
  "updated": "2026-03-12T18:35:35.452862+00:00",
  "status": "LIVE",
  "trading_mode": "PAPER",
  "bars_processed": 200,
  "trades_today": 23,
  "win_rate": 47.8,
  "profit_factor": 2.09,
  "session_pnl_pct": 1.486,
  "signals_rejected": 0,
  "signals_approved": 13,
  "htf_bias": "NEUTRAL",
  "safety_rails": "OK",
  "modifiers": {
    "overnight": {
      "value": 1.0,
      "display": "1.0x (neutral)"
    },
    "fomc": {
      "value": 1.0,
      "display": "1.0x (no_fomc)"
    },
    "gamma": {
      "value": 1.0,
      "display": "1.0x (VIX data unavailable)"
    },
    "har_rv": {
      "value": 1.1,
      "display": "1.1x (RV 50th percentile (below avg vol), log_rv=-8.98)"
    }
  },
  "last_price": 24614.75,
  "recent_decisions": [
    {
      "time": "14:28:55 ET",
      "direction": "",
      "decision": "",
      "reason": "Approved"
    },
    {
      "time": "14:31:00 ET",
      "direction": "LONG",
      "decision": "EXIT",
      "reason": "Approved"
    },
    {
      "time": "14:31:40 ET",
      "direction": "LONG",
      "decision": "APPROVED",
      "reason": "Approved"
    },
    {
      "time": "14:33:45 ET",
      "direction": "LONG",
      "decision": "EXIT",
      "reason": "Approved"
    },
    {
      "time": "14:33:50 ET",
      "direction": "LONG",
      "decision": "APPROVED",
      "reason": "Approved"
    },
    {
      "time": "",
      "direction": "",
      "decision": "",
      "reason": "Approved"
    },
    {
      "time": "14:34:17 ET",
      "direction": "",
      "decision": "",
      "reason": "Approved"
    },
    {
      "time": "14:34:40 ET",
      "direction": "LONG",
      "decision": "EXIT",
      "reason": "Approved"
    },
    {
      "time": "14:34:45 ET",
      "direction": "LONG",
      "decision": "APPROVED",
      "reason": "Approved"
    },
    {
      "time": "14:34:45 ET",
      "direction": "",
      "decision": "",
      "reason": "Approved"
    }
  ],
  "heartbeat": {
    "last_seen": "2026-03-11T17:37:35.115789+00:00",
    "seconds_since_last": 89880.3,
    "connection_quality": "good",
    "uptime_pct": 100.0
  },
  "state": {
    "mode": "TRADING",
    "last_trade_time": "14:34:45 ET",
    "active_positions": 0
  },
  "active_trade": null,
  "candle_buffer": [
    {
      "t": "",
      "o": 24640.0,
      "h": 24645.5,
      "l": 24640.0,
      "c": 24645.25
    },
    {
      "t": "",
      "o": 24644.5,
      "h": 24646.0,
      "l": 24640.25,
      "c": 24641.25
    },
    {
      "t": "",
      "o": 24640.75,
      "h": 24644.25,
      "l": 24640.75,
      "c": 24643.75
    },
    {
      "t": "",
      "o": 24643.75,
      "h": 24643.75,
      "l": 24634.75,
      "c": 24637.25
    },
    {
      "t": "",
      "o": 24637.0,
      "h": 24641.75,
      "l": 24636.5,
      "c": 24640.5
    },
    {
      "t": "",
      "o": 24640.0,
      "h": 24641.25,
      "l": 24639.25,
      "c": 24639.75
    },
    {
      "t": "",
      "o": 24640.0,
      "h": 24641.0,
      "l": 24639.0,
      "c": 24641.0
    },
    {
      "t": "",
      "o": 24641.75,
      "h": 24643.25,
      "l": 24639.5,
      "c": 24640.0
    },
    {
      "t": "",
      "o": 24640.25,
      "h": 24645.5,
      "l": 24639.5,
      "c": 24644.0
    },
    {
      "t": "",
      "o": 24644.25,
      "h": 24645.0,
      "l": 24642.5,
      "c": 24644.5
    },
    {
      "t": "",
      "o": 24644.5,
      "h": 24646.5,
      "l": 24643.75,
      "c": 24645.25
    },
    {
      "t": "",
      "o": 24645.5,
      "h": 24645.5,
      "l": 24642.0,
      "c": 24644.0
    },
    {
      "t": "",
      "o": 24644.0,
      "h": 24645.0,
      "l": 24640.5,
      "c": 24640.5
    },
    {
      "t": "",
      "o": 24641.0,
      "h": 24643.25,
      "l": 24639.0,
      "c": 24642.5
    },
    {
      "t": "",
      "o": 24643.0,
      "h": 24645.25,
      "l": 24641.5,
      "c": 24642.75
    },
    {
      "t": "",
      "o": 24642.5,
      "h": 24642.75,
      "l": 24638.75,
      "c": 24639.25
    },
    {
      "t": "",
      "o": 24638.75,
      "h": 24639.75,
      "l": 24638.5,
      "c": 24639.75
    },
    {
      "t": "",
      "o": 24639.75,
      "h": 24640.5,
      "l": 24639.5,
      "c": 24640.25
    },
    {
      "t": "",
      "o": 24640.0,
      "h": 24640.25,
      "l": 24637.0,
      "c": 24639.0
    },
    {
      "t": "",
      "o": 24640.5,
      "h": 24640.5,
      "l": 24638.5,
      "c": 24639.25
    },
    {
      "t": "",
      "o": 24638.75,
      "h": 24639.25,
      "l": 24635.25,
      "c": 24635.25
    },
    {
      "t": "",
      "o": 24635.25,
      "h": 24637.0,
      "l": 24632.75,
      "c": 24637.0
    },
    {
      "t": "",
      "o": 24637.25,
      "h": 24638.25,
      "l": 24636.0,
      "c": 24636.75
    },
    {
      "t": "",
      "o": 24636.75,
      "h": 24637.75,
      "l": 24633.5,
      "c": 24635.0
    },
    {
      "t": "",
      "o": 24634.75,
      "h": 24634.75,
      "l": 24630.0,
      "c": 24633.5
    },
    {
      "t": "",
      "o": 24633.5,
      "h": 24634.0,
      "l": 24628.25,
      "c": 24628.25
    },
    {
      "t": "",
      "o": 24628.75,
      "h": 24629.0,
      "l": 24626.0,
      "c": 24627.0
    },
    {
      "t": "",
      "o": 24626.5,
      "h": 24627.0,
      "l": 24625.25,
      "c": 24625.5
    },
    {
      "t": "",
      "o": 24625.75,
      "h": 24626.0,
      "l": 24617.25,
      "c": 24618.5
    },
    {
      "t": "",
      "o": 24619.0,
      "h": 24620.75,
      "l": 24615.75,
      "c": 24617.5
    },
    {
      "t": "",
      "o": 24617.0,
      "h": 24619.25,
      "l": 24616.0,
      "c": 24619.0
    },
    {
      "t": "",
      "o": 24618.75,
      "h": 24623.75,
      "l": 24618.75,
      "c": 24622.0
    },
    {
      "t": "",
      "o": 24621.5,
      "h": 24622.0,
      "l": 24617.5,
      "c": 24619.0
    },
    {
      "t": "",
      "o": 24619.25,
      "h": 24620.0,
      "l": 24616.25,
      "c": 24616.75
    },
    {
      "t": "",
      "o": 24616.0,
      "h": 24616.0,
      "l": 24613.5,
      "c": 24613.5
    },
    {
      "t": "",
      "o": 24613.5,
      "h": 24617.25,
      "l": 24612.75,
      "c": 24616.75
    },
    {
      "t": "",
      "o": 24617.0,
      "h": 24623.5,
      "l": 24616.75,
      "c": 24621.0
    },
    {
      "t": "",
      "o": 24621.0,
      "h": 24621.0,
      "l": 24615.0,
      "c": 24615.25
    },
    {
      "t": "",
      "o": 24614.75,
      "h": 24617.5,
      "l": 24614.0,
      "c": 24617.0
    },
    {
      "t": "",
      "o": 24617.0,
      "h": 24617.5,
      "l": 24614.0,
      "c": 24614.75
    }
  ]
}